README.md
setup.py
gctime.egg-info/PKG-INFO
gctime.egg-info/SOURCES.txt
gctime.egg-info/dependency_links.txt
gctime.egg-info/entry_points.txt
gctime.egg-info/not-zip-safe
gctime.egg-info/requires.txt
gctime.egg-info/top_level.txt
lccommon/__init__.py
lccommon/data_types.py
lccommon/net_util.py
lccommon/spice_parser.py
lctime/__init__.py
lctime/cell_types.py
lctime/licence.py
lctime/characterization/__init__.py
lctime/characterization/input_capacitance.py
lctime/characterization/main_lctime.py
lctime/characterization/main_sp2bool.py
lctime/characterization/ngspice_simulation.py
lctime/characterization/ngspice_subprocess.py
lctime/characterization/piece_wise_linear.py
lctime/characterization/test_ngspice_shared.py
lctime/characterization/test_ngspice_subprocess.py
lctime/characterization/timing_combinatorial.py
lctime/characterization/timing_sequential.py
lctime/characterization/util.py
lctime/liberty/__init__.py
lctime/liberty/merge.py
lctime/liberty/util.py
lctime/liberty/visualize.py
lctime/logic/__init__.py
lctime/logic/cmos_sim.py
lctime/logic/cmos_synth.py
lctime/logic/functional_abstraction.py
lctime/logic/graph_enumeration.py
lctime/logic/seq_recognition.py
lctime/logic/smt_4value_logic_scratch.py
lctime/logic/types.py
lctime/logic/util.py
lctime/transistor_sizing/__init__.py