Metadata-Version: 2.1
Name: gctime
Version: 0.0.17
Summary: CMOS standard-cell characterization kit.
Home-page: https://codeberg.org/gnucell/gctime
Author: T. Kramer
Author-email: code@tkramer.ch
License: GPL-3.0-or-later
Keywords: cmos cell characterization vlsi asic
Platform: UNKNOWN
Classifier: License :: OSI Approved :: GNU General Public License v3 or later (GPLv3+)
Classifier: Development Status :: 3 - Alpha
Classifier: Topic :: Scientific/Engineering
Classifier: Topic :: Scientific/Engineering :: Electronic Design Automation (EDA)
Classifier: Programming Language :: Python :: 3
